microdrop_launcher/__init__.py
microdrop_launcher/auto_upgrade.py
microdrop_launcher/config.py
microdrop_launcher/dirs.py
microdrop_launcher/profile.py
microdrop_launcher/test.py
microdrop_launcher/uname.exe.stackdump
microdrop_launcher/windows.py
microdrop_launcher/bin/__init__.py
microdrop_launcher/bin/create_config_directory.py
microdrop_launcher/bin/diff.exe.stackdump
microdrop_launcher/bin/launch.py
microdrop_launcher/bin/profile_launcher.py
microdrop_launcher/glade/import-dialog.glade
microdrop_launcher-0.1.post66.dist-info/DESCRIPTION.rst
microdrop_launcher-0.1.post66.dist-info/METADATA
microdrop_launcher-0.1.post66.dist-info/RECORD
microdrop_launcher-0.1.post66.dist-info/WHEEL
microdrop_launcher-0.1.post66.dist-info/entry_points.txt
microdrop_launcher-0.1.post66.dist-info/metadata.json
microdrop_launcher-0.1.post66.dist-info/top_level.txt
